chuk_puzzles_gym/__init__.py
chuk_puzzles_gym/constants.py
chuk_puzzles_gym/eval.py
chuk_puzzles_gym/gym_env.py
chuk_puzzles_gym/server.py
chuk_puzzles_gym/export/__init__.py
chuk_puzzles_gym/export/dataset.py
chuk_puzzles_gym/games/__init__.py
chuk_puzzles_gym/games/_base/__init__.py
chuk_puzzles_gym/games/_base/commands.py
chuk_puzzles_gym/games/_base/game.py
chuk_puzzles_gym/games/binary/__init__.py
chuk_puzzles_gym/games/binary/config.py
chuk_puzzles_gym/games/binary/game.py
chuk_puzzles_gym/games/bridges/__init__.py
chuk_puzzles_gym/games/bridges/config.py
chuk_puzzles_gym/games/bridges/game.py
chuk_puzzles_gym/games/cryptarithmetic/__init__.py
chuk_puzzles_gym/games/cryptarithmetic/commands.py
chuk_puzzles_gym/games/cryptarithmetic/config.py
chuk_puzzles_gym/games/cryptarithmetic/game.py
chuk_puzzles_gym/games/einstein/__init__.py
chuk_puzzles_gym/games/einstein/config.py
chuk_puzzles_gym/games/einstein/constants.py
chuk_puzzles_gym/games/einstein/game.py
chuk_puzzles_gym/games/einstein/models.py
chuk_puzzles_gym/games/fillomino/__init__.py
chuk_puzzles_gym/games/fillomino/config.py
chuk_puzzles_gym/games/fillomino/game.py
chuk_puzzles_gym/games/futoshiki/__init__.py
chuk_puzzles_gym/games/futoshiki/config.py
chuk_puzzles_gym/games/futoshiki/game.py
chuk_puzzles_gym/games/graph_coloring/__init__.py
chuk_puzzles_gym/games/graph_coloring/commands.py
chuk_puzzles_gym/games/graph_coloring/config.py
chuk_puzzles_gym/games/graph_coloring/game.py
chuk_puzzles_gym/games/hidato/__init__.py
chuk_puzzles_gym/games/hidato/config.py
chuk_puzzles_gym/games/hidato/game.py
chuk_puzzles_gym/games/hitori/__init__.py
chuk_puzzles_gym/games/hitori/config.py
chuk_puzzles_gym/games/hitori/game.py
chuk_puzzles_gym/games/kakuro/__init__.py
chuk_puzzles_gym/games/kakuro/config.py
chuk_puzzles_gym/games/kakuro/game.py
chuk_puzzles_gym/games/kenken/__init__.py
chuk_puzzles_gym/games/kenken/config.py
chuk_puzzles_gym/games/kenken/enums.py
chuk_puzzles_gym/games/kenken/game.py
chuk_puzzles_gym-0.10.dist-info/METADATA
chuk_puzzles_gym-0.10.dist-info/WHEEL
chuk_puzzles_gym-0.10.dist-info/entry_points.txt
chuk_puzzles_gym-0.10.dist-info/top_level.txt
chuk_puzzles_gym-0.10.dist-info/RECORD
